py_askpass-0.0.0.data/data/bin/pssh
pyaskpass/__init__.py
pyaskpass/main.py
pyaskpass/pssh
py_askpass-0.0.0.dist-info/METADATA
py_askpass-0.0.0.dist-info/WHEEL
py_askpass-0.0.0.dist-info/entry_points.txt
py_askpass-0.0.0.dist-info/top_level.txt
py_askpass-0.0.0.dist-info/RECORD
