Metadata-Version: 2.4
Name: py-askpass
Version: 0.0.0
Summary: SSH Wrapper with Password and TOTP Support
Author: Chon-Hei Lo
License: MIT
Project-URL: Homepage, https://github.com/hheei/py-askpass
Project-URL: Repository, https://github.com/hheei/py-askpass
Project-URL: Issues, https://github.com/hheei/py-askpass/issues
Keywords: ssh,password,totp,authentication,wrapper
Classifier: Development Status :: 4 - Beta
Classifier: Intended Audience :: Developers
Classifier: Intended Audience :: System Administrators
Classifier: License :: OSI Approved :: MIT License
Classifier: Operating System :: OS Independent
Classifier: Programming Language :: Python :: 3
Classifier: Programming Language :: Python :: 3.9
Classifier: Programming Language :: Python :: 3.10
Classifier: Programming Language :: Python :: 3.11
Classifier: Programming Language :: Python :: 3.12
Classifier: Topic :: System :: Systems Administration
Classifier: Topic :: Utilities
Requires-Python: >=3.9
Requires-Dist: pyotp>=2.8.0
